{
  "project_info": {
    "project_number": "45690276205",
    "firebase_url": "https://flash-chat-3adfb.firebaseio.com",
    "project_id": "flash-chat-3adfb",
    "storage_bucket": "flash-chat-3adfb.appspot.com"
  },
  "client": [
    {
      "client_info": {
        "mobilesdk_app_id": "1:45690276205:android:a69f2e5e4135dc053b3264",
        "android_client_info": {
          "package_name": "co.appbrewery.flash_chat"
        }
      },
      "oauth_client": [
        {
          "client_id": "45690276205-4p08kij8fj15i339tk23ihm4vtrbng1c.apps.googleusercontent.com",
          "client_type": 3
        }
      ],
      "api_key": [
        {
          "current_key": "AIzaSyDKV6YdR1yrlqodpsgq8yuYos0oC6Pdo60"
        }
      ],
      "services": {
        "appinvite_service": {
          "other_platform_oauth_client": [
            {
              "client_id": "45690276205-4p08kij8fj15i339tk23ihm4vtrbng1c.apps.googleusercontent.com",
              "client_type": 3
            }
          ]
        }
      }
    }
  ],
  "configuration_version": "1"
}